[
    {
        "id": 1,
        "created_by_company": null,
        "group": 1,
        "catid": 1,
        "account_type": "1",
        "customer_salutation": "Mr.",
        "first_name": "Shwetha",
        "last_name": "Nambiar",
        "name": "Datazone Systems Llc",
        "customer_name_display": "DATAZONE SYSTEMS LLC",
        "code": "CUS-1001",
        "address": null,
        "address2": null,
        "country_telephone": "AE|231",
        "contcat_person": "Shwetha",
        "designation": "Procurement Manager",
        "contcat_number": "+971 4 220 6922",
        "mobile": "+971 50 718 9544",
        "email": "shwetha@datazoneme.com",
        "sales_person": 132,
        "vat_type": null,
        "purchase_type": null,
        "customer_type": 5,
        "sale_type": 5,
        "supplier_type": null,
        "vat_country": "231",
        "vat_state": "3391",
        "vat_percentage": "5",
        "vat_number": "100530261500003",
        "credit_limit": "100000.000",
        "credit_days": 30,
        "payment_terms": 6,
        "payment_terms_txt": "",
        "transaction_type": "Credit",
        "customer_documents": null,
        "status": 1,
        "created_by": 1,
        "updated_by": 1,
        "created_at": "2026-01-23 18:18:06",
        "updated_at": "2026-01-23 22:18:06",
        "type": 1,
        "company_id": 2,
        "vat_is_fixed": 0,
        "city": "RAS AL KHOR",
        "zip_code": "",
        "company_access": "1",
        "is_file": 1,
        "vendor_name": null,
        "beneficiary_name": null,
        "iban": null,
        "swift_code": null,
        "city_country": null,
        "stl": 0,
        "stl_bank": null,
        "stl_limit": null,
        "stl_per_trn_limit": null,
        "stl_opb": null,
        "internal": 0,
        "area": "INDUSTRIAL THIRD",
        "building_name": "THE FRESH MARKET",
        "flat_office_no": "D-06,",
        "website": "https:\/\/www.datazoneme.com\/",
        "maps_location": "https:\/\/maps.google.com\/?cid=6703558181248810949",
        "place_id": "ChIJ____P9ddXz4Rxb9_HKbSB10",
        "taken_from_stock": null,
        "stock_order": null,
        "customer_id": null,
        "supplier_id": null,
        "company_ship_to_id": null,
        "grn_select": null
    },
    {
        "id": 2,
        "created_by_company": null,
        "group": 2,
        "catid": 2,
        "account_type": null,
        "customer_salutation": null,
        "first_name": "Zeba",
        "last_name": "Cyrus Sheffi",
        "name": "Redington Middle East LLC",
        "customer_name_display": "REDINGTON MIDDLE EAST LLC",
        "code": "SUPSD-1001",
        "address": null,
        "address2": null,
        "country_telephone": "AE|231",
        "contcat_person": "Zeba",
        "designation": "Account Manager",
        "contcat_number": "+971 4 516 1000",
        "mobile": "+971 56 501 6792",
        "email": "zeba.cyrus@redingtongroup.com",
        "sales_person": 1,
        "vat_type": null,
        "purchase_type": 6,
        "customer_type": null,
        "sale_type": null,
        "supplier_type": 5,
        "vat_country": "231",
        "vat_state": "3391",
        "vat_percentage": "5",
        "vat_number": "100245109200003",
        "credit_limit": "5500000.000",
        "credit_days": 60,
        "payment_terms": 4,
        "payment_terms_txt": "",
        "transaction_type": "Credit",
        "customer_documents": null,
        "status": 1,
        "created_by": 1,
        "updated_by": 1,
        "created_at": "2026-01-15 16:14:40",
        "updated_at": "2026-01-15 20:14:40",
        "type": null,
        "company_id": 1,
        "vat_is_fixed": 1,
        "city": "Opp Trade Centre",
        "zip_code": "17266",
        "company_access": "1",
        "is_file": 1,
        "vendor_name": "",
        "beneficiary_name": "",
        "iban": "",
        "swift_code": "",
        "city_country": "",
        "stl": 0,
        "stl_bank": null,
        "stl_limit": null,
        "stl_per_trn_limit": null,
        "stl_opb": null,
        "internal": 0,
        "area": "Shaikh Zayed Road",
        "building_name": "H Hotel Office Towers",
        "flat_office_no": "7th Floor",
        "website": "https:\/\/redingtongroup.com\/#",
        "maps_location": "https:\/\/maps.app.goo.gl\/4y5MhW3QLFa6hA2c6",
        "place_id": null,
        "taken_from_stock": null,
        "stock_order": null,
        "customer_id": null,
        "supplier_id": null,
        "company_ship_to_id": null,
        "grn_select": null
    },
    {
        "id": 3,
        "created_by_company": null,
        "group": 2,
        "catid": 2,
        "account_type": "1",
        "customer_salutation": "Mr.",
        "first_name": "Navid",
        "last_name": "Qureshi",
        "name": "Logicom Dubai LLC",
        "customer_name_display": "LOGICOM DUBAI LLC",
        "code": "SUPSD-1002",
        "address": null,
        "address2": null,
        "country_telephone": "AE|231",
        "contcat_person": "Navid",
        "designation": "Account Manager",
        "contcat_number": "+971 4 805 5399",
        "mobile": "+971 50 8047478 \/ +97156 6819891",
        "email": "n.qureshi@logicom.net",
        "sales_person": 1,
        "vat_type": null,
        "purchase_type": 6,
        "customer_type": null,
        "sale_type": null,
        "supplier_type": 5,
        "vat_country": "231",
        "vat_state": "3391",
        "vat_percentage": "5",
        "vat_number": "110",
        "credit_limit": "3500000.000",
        "credit_days": 60,
        "payment_terms": 8,
        "payment_terms_txt": "",
        "transaction_type": "Credit",
        "customer_documents": null,
        "status": 1,
        "created_by": 1,
        "updated_by": 1,
        "created_at": "2026-01-30 20:08:24",
        "updated_at": "2026-01-31 00:08:24",
        "type": 1,
        "company_id": 1,
        "vat_is_fixed": 1,
        "city": "Jebel Ali",
        "zip_code": "54328",
        "company_access": "1",
        "is_file": 1,
        "vendor_name": "",
        "beneficiary_name": "",
        "iban": "",
        "swift_code": "",
        "city_country": "",
        "stl": 0,
        "stl_bank": null,
        "stl_limit": null,
        "stl_per_trn_limit": null,
        "stl_opb": null,
        "internal": 0,
        "area": "South Zone 6",
        "building_name": "Plot No: S60608",
        "flat_office_no": "Street No.S1503",
        "website": "https:\/\/distribution.logicom.net\/countries\/logicom-gulf\/",
        "maps_location": "https:\/\/maps.google.com\/?cid=2273636950296273559",
        "place_id": null,
        "taken_from_stock": null,
        "stock_order": null,
        "customer_id": null,
        "supplier_id": null,
        "company_ship_to_id": null,
        "grn_select": null
    },
    {
        "id": 4,
        "created_by_company": null,
        "group": 1,
        "catid": 1,
        "account_type": "1",
        "customer_salutation": "Mr",
        "first_name": "Naushad",
        "last_name": "Abdul Wahid",
        "name": "Stack Link General Trading Llc",
        "customer_name_display": "STACK LINK GENERAL TRADING LLC",
        "code": "CUSSD-1001",
        "address": null,
        "address2": null,
        "country_telephone": "AE|231",
        "contcat_person": "Naushad",
        "designation": "Procurement Manager",
        "contcat_number": "+971 4 3858883",
        "mobile": "+971 52 924 2884",
        "email": "abdul@slinkllc.com",
        "sales_person": 132,
        "vat_type": null,
        "purchase_type": null,
        "customer_type": 5,
        "sale_type": 5,
        "supplier_type": null,
        "vat_country": "231",
        "vat_state": "3391",
        "vat_percentage": "5",
        "vat_number": "100295722100003",
        "credit_limit": "1500000.000",
        "credit_days": 60,
        "payment_terms": 8,
        "payment_terms_txt": "",
        "transaction_type": "Credit",
        "customer_documents": null,
        "status": 1,
        "created_by": 1,
        "updated_by": 1,
        "created_at": "2026-01-20 16:21:06",
        "updated_at": "2026-01-20 20:21:06",
        "type": 1,
        "company_id": 1,
        "vat_is_fixed": 0,
        "city": "BUR DUBAI",
        "zip_code": "48689",
        "company_access": "1,2",
        "is_file": 1,
        "vendor_name": null,
        "beneficiary_name": null,
        "iban": null,
        "swift_code": null,
        "city_country": null,
        "stl": 0,
        "stl_bank": null,
        "stl_limit": null,
        "stl_per_trn_limit": null,
        "stl_opb": null,
        "internal": 0,
        "area": "BUR DUBAI",
        "building_name": "11",
        "flat_office_no": "11",
        "website": "https:\/\/slinkllc.com\/",
        "maps_location": "https:\/\/maps.google.com\/?cid=7210978533414724806",
        "place_id": "ChIJO3yVm5hDXz4RxuQmT8WKEmQ",
        "taken_from_stock": null,
        "stock_order": null,
        "customer_id": null,
        "supplier_id": null,
        "company_ship_to_id": null,
        "grn_select": null
    },
    {
        "id": 5,
        "created_by_company": null,
        "group": 1,
        "catid": 1,
        "account_type": "1",
        "customer_salutation": "Mr.",
        "first_name": "Dgfdfg",
        "last_name": "Dfgdfg",
        "name": "Testbeddgr",
        "customer_name_display": "TESTBEDDGR",
        "code": "CUSSD-1002",
        "address": null,
        "address2": null,
        "country_telephone": "GB|232",
        "contcat_person": "Dgfdfg",
        "designation": "Procurement Manager",
        "contcat_number": "+44 113 403 4463",
        "mobile": "+44 113 403 4463",
        "email": "derte@abcd.com",
        "sales_person": 133,
        "vat_type": null,
        "purchase_type": null,
        "customer_type": 5,
        "sale_type": 5,
        "supplier_type": null,
        "vat_country": "232",
        "vat_state": "2291",
        "vat_percentage": "20",
        "vat_number": "cx5465465",
        "credit_limit": "0.000",
        "credit_days": 0,
        "payment_terms": 3,
        "payment_terms_txt": "",
        "transaction_type": "Cash",
        "customer_documents": null,
        "status": 1,
        "created_by": 1,
        "updated_by": 133,
        "created_at": "2026-01-28 13:35:52",
        "updated_at": "2026-01-28 17:35:52",
        "type": 1,
        "company_id": 1,
        "vat_is_fixed": 0,
        "city": "abc",
        "zip_code": "LS10 1ES1416",
        "company_access": "1",
        "is_file": 0,
        "vendor_name": null,
        "beneficiary_name": null,
        "iban": null,
        "swift_code": null,
        "city_country": null,
        "stl": 0,
        "stl_bank": null,
        "stl_limit": null,
        "stl_per_trn_limit": null,
        "stl_opb": null,
        "internal": 0,
        "area": "test",
        "building_name": "1131",
        "flat_office_no": "13456",
        "website": "http:\/\/www.testbedleeds.com\/",
        "maps_location": "https:\/\/maps.google.com\/?cid=5213475345174133696",
        "place_id": "ChIJUYNQCNJdeUgRwHtcSjT8WUg",
        "taken_from_stock": null,
        "stock_order": null,
        "customer_id": null,
        "supplier_id": null,
        "company_ship_to_id": null,
        "grn_select": null
    },
    {
        "id": 6,
        "created_by_company": null,
        "group": 2,
        "catid": 2,
        "account_type": "1",
        "customer_salutation": "Mr.",
        "first_name": "Bianca",
        "last_name": "Bhatia",
        "name": "NETWORK DISTRIBUTORS FZ LLC",
        "customer_name_display": "NETWORK DISTRIBUTORS FZ LLC",
        "code": "SUPSD-1003",
        "address": null,
        "address2": null,
        "country_telephone": "AE|231",
        "contcat_person": "Bianca",
        "designation": "Account Manager",
        "contcat_number": "+9714434 7374",
        "mobile": "+97156174 0832",
        "email": "bbhatia@exclusive-networks.com",
        "sales_person": 1,
        "vat_type": null,
        "purchase_type": 6,
        "customer_type": null,
        "sale_type": null,
        "supplier_type": 5,
        "vat_country": "231",
        "vat_state": "3391",
        "vat_percentage": "5",
        "vat_number": "100375068200003",
        "credit_limit": "1500000.000",
        "credit_days": 60,
        "payment_terms": 3,
        "payment_terms_txt": "",
        "transaction_type": "Credit",
        "customer_documents": null,
        "status": 1,
        "created_by": 1,
        "updated_by": 1,
        "created_at": "2026-02-07 18:37:03",
        "updated_at": "2026-02-07 22:37:03",
        "type": 1,
        "company_id": 1,
        "vat_is_fixed": 0,
        "city": "Dubai Media City",
        "zip_code": "500640",
        "company_access": "1,2,3",
        "is_file": 1,
        "vendor_name": "",
        "beneficiary_name": "",
        "iban": "",
        "swift_code": "",
        "city_country": "",
        "stl": 0,
        "stl_bank": null,
        "stl_limit": null,
        "stl_per_trn_limit": null,
        "stl_opb": null,
        "internal": 0,
        "area": "Shaikh Zayed Road",
        "building_name": "Shatha Tower",
        "flat_office_no": "35th Floor",
        "website": "https:\/\/www.exclusive-networks.com\/ae\/",
        "maps_location": "",
        "place_id": null,
        "taken_from_stock": null,
        "stock_order": null,
        "customer_id": null,
        "supplier_id": null,
        "company_ship_to_id": null,
        "grn_select": null
    },
    {
        "id": 7,
        "created_by_company": null,
        "group": 1,
        "catid": 1,
        "account_type": "1",
        "customer_salutation": "Miss",
        "first_name": "Shekha",
        "last_name": "Mendoza",
        "name": "Absons IT Solutions & Equipment",
        "customer_name_display": "ABSONS IT SOLUTIONS & EQUIPMENT",
        "code": "CUSSD-1003",
        "address": null,
        "address2": null,
        "country_telephone": "AE|231",
        "contcat_person": "Shekha",
        "designation": "Procurement Manager",
        "contcat_number": "+971 2 441 0590",
        "mobile": "+971 56 688 2368",
        "email": "shekha.mendoza@absons.ae",
        "sales_person": 1,
        "vat_type": null,
        "purchase_type": null,
        "customer_type": 5,
        "sale_type": 5,
        "supplier_type": null,
        "vat_country": "231",
        "vat_state": "3396",
        "vat_percentage": "5",
        "vat_number": "100351269400003",
        "credit_limit": "150000.000",
        "credit_days": 30,
        "payment_terms": 9,
        "payment_terms_txt": "",
        "transaction_type": "Credit",
        "customer_documents": null,
        "status": 1,
        "created_by": 1,
        "updated_by": 1,
        "created_at": "2026-01-16 21:31:40",
        "updated_at": "2026-01-17 01:31:40",
        "type": 1,
        "company_id": 1,
        "vat_is_fixed": 0,
        "city": "Old Airport Road",
        "zip_code": "6152",
        "company_access": "1",
        "is_file": 1,
        "vendor_name": null,
        "beneficiary_name": null,
        "iban": null,
        "swift_code": null,
        "city_country": null,
        "stl": 0,
        "stl_bank": null,
        "stl_limit": null,
        "stl_per_trn_limit": null,
        "stl_opb": null,
        "internal": 0,
        "area": "Al Manhal- W14-02",
        "building_name": "Arabian Company",
        "flat_office_no": "5th Floor",
        "website": "https:\/\/www.absons.ae\/",
        "maps_location": "https:\/\/maps.google.com\/?cid=3854074090482346838",
        "place_id": "ChIJIYUqnCNmXj4RVqs8LfdrfDU",
        "taken_from_stock": null,
        "stock_order": null,
        "customer_id": null,
        "supplier_id": null,
        "company_ship_to_id": null,
        "grn_select": null
    },
    {
        "id": 8,
        "created_by_company": null,
        "group": 1,
        "catid": 1,
        "account_type": "1",
        "customer_salutation": null,
        "first_name": "Ranjeeth",
        "last_name": "",
        "name": "NEW TREND COMPUTER NETWORKS LLC",
        "customer_name_display": "NEW TREND COMPUTER NETWORKS LLC",
        "code": "CUSD-1001",
        "address": null,
        "address2": null,
        "country_telephone": "AE|231",
        "contcat_person": null,
        "designation": "Purchase",
        "contcat_number": "+971 4 393 1145",
        "mobile": "+971 4 393 1145",
        "email": "cheriyan@newtrend.ae",
        "sales_person": 132,
        "vat_type": "",
        "purchase_type": null,
        "customer_type": 5,
        "sale_type": 5,
        "supplier_type": null,
        "vat_country": "231",
        "vat_state": "3391",
        "vat_percentage": "5",
        "vat_number": "100372913200003",
        "credit_limit": "1.000",
        "credit_days": 1,
        "payment_terms": 6,
        "payment_terms_txt": null,
        "transaction_type": null,
        "customer_documents": null,
        "status": 3,
        "created_by": 1,
        "updated_by": 1,
        "created_at": "2026-01-25 16:46:56",
        "updated_at": "2026-01-25 20:46:56",
        "type": 1,
        "company_id": 1,
        "vat_is_fixed": 0,
        "city": null,
        "zip_code": null,
        "company_access": "1,1",
        "is_file": 1,
        "vendor_name": null,
        "beneficiary_name": null,
        "iban": null,
        "swift_code": null,
        "city_country": null,
        "stl": 0,
        "stl_bank": null,
        "stl_limit": null,
        "stl_per_trn_limit": null,
        "stl_opb": null,
        "internal": 0,
        "area": "Khalid Bin Walid Street",
        "building_name": "Al Fahidi",
        "flat_office_no": "4",
        "website": "http:\/\/www.newtrend.ae\/",
        "maps_location": "https:\/\/maps.google.com\/?cid=5973669110277976213",
        "place_id": "ChIJY7mDixRDXz4RlbDX62e85lI",
        "taken_from_stock": null,
        "stock_order": null,
        "customer_id": null,
        "supplier_id": null,
        "company_ship_to_id": null,
        "grn_select": null
    },
    {
        "id": 9,
        "created_by_company": null,
        "group": 2,
        "catid": 2,
        "account_type": null,
        "customer_salutation": null,
        "first_name": "Usman",
        "last_name": "Mohammad",
        "name": "APTEC DISTRIBUTION FZ LLC",
        "customer_name_display": "APTEC DISTRIBUTION FZ LLC",
        "code": "SUPD-1001",
        "address": null,
        "address2": null,
        "country_telephone": "AE|231",
        "contcat_person": "Usman",
        "designation": "Chief Financial Officer (CFO)",
        "contcat_number": "+971 4 369 7111",
        "mobile": "",
        "email": "mohamedmontasser.salaheldin@ingrammicro.com",
        "sales_person": 1,
        "vat_type": null,
        "purchase_type": 6,
        "customer_type": null,
        "sale_type": null,
        "supplier_type": 5,
        "vat_country": "231",
        "vat_state": "3391",
        "vat_percentage": "5",
        "vat_number": "100273713600003",
        "credit_limit": "1500000.000",
        "credit_days": 60,
        "payment_terms": 8,
        "payment_terms_txt": "",
        "transaction_type": "Credit",
        "customer_documents": null,
        "status": 1,
        "created_by": 1,
        "updated_by": null,
        "created_at": "2026-01-25 17:03:08",
        "updated_at": "2026-01-25 23:03:08",
        "type": 1,
        "company_id": 1,
        "vat_is_fixed": 0,
        "city": "Internet City",
        "zip_code": null,
        "company_access": "1",
        "is_file": 2,
        "vendor_name": "",
        "beneficiary_name": "",
        "iban": "",
        "swift_code": "",
        "city_country": "",
        "stl": 0,
        "stl_bank": null,
        "stl_limit": null,
        "stl_per_trn_limit": null,
        "stl_opb": null,
        "internal": 0,
        "area": "Innovation Hub",
        "building_name": "Building 1",
        "flat_office_no": "1st & 2nd Floor, DIC",
        "website": "http:\/\/meta.ingrammicro.com\/",
        "maps_location": "https:\/\/maps.google.com\/?cid=9272144126323672608",
        "place_id": null,
        "taken_from_stock": null,
        "stock_order": null,
        "customer_id": null,
        "supplier_id": null,
        "company_ship_to_id": null,
        "grn_select": null
    },
    {
        "id": 10,
        "created_by_company": null,
        "group": 1,
        "catid": 1,
        "account_type": "1",
        "customer_salutation": "Mr.",
        "first_name": "Mr.",
        "last_name": "Subeesh",
        "name": "Goodwill Infotech Llc",
        "customer_name_display": "GOODWILL INFOTECH LLC",
        "code": "CUSD-1002",
        "address": null,
        "address2": null,
        "country_telephone": "AE|231",
        "contcat_person": "Mr.",
        "designation": "Purchase",
        "contcat_number": "+971 4 522 9229",
        "mobile": "+971 4 522 9229",
        "email": "subeesh@goodwill.com",
        "sales_person": 141,
        "vat_type": "",
        "purchase_type": null,
        "customer_type": 5,
        "sale_type": 5,
        "supplier_type": null,
        "vat_country": "231",
        "vat_state": "3391",
        "vat_percentage": "5",
        "vat_number": "1234568913",
        "credit_limit": "1.000",
        "credit_days": 1,
        "payment_terms": 6,
        "payment_terms_txt": "",
        "transaction_type": "Credit",
        "customer_documents": null,
        "status": 1,
        "created_by": 1,
        "updated_by": 1,
        "created_at": "2026-03-26 13:46:13",
        "updated_at": "2026-03-26 17:46:13",
        "type": 1,
        "company_id": 1,
        "vat_is_fixed": 0,
        "city": "Bur Dubai",
        "zip_code": "123456",
        "company_access": "1,2",
        "is_file": 1,
        "vendor_name": null,
        "beneficiary_name": null,
        "iban": null,
        "swift_code": null,
        "city_country": null,
        "stl": 0,
        "stl_bank": null,
        "stl_limit": null,
        "stl_per_trn_limit": null,
        "stl_opb": null,
        "internal": 0,
        "area": "Khalid Bin Walid Street",
        "building_name": "Dafoos Building",
        "flat_office_no": "105",
        "website": "http:\/\/www.goodwillinfotech.com\/",
        "maps_location": "https:\/\/maps.google.com\/?cid=16612405717955079847",
        "place_id": null,
        "taken_from_stock": null,
        "stock_order": null,
        "customer_id": null,
        "supplier_id": null,
        "company_ship_to_id": null,
        "grn_select": "yes"
    },
    {
        "id": 11,
        "created_by_company": null,
        "group": 1,
        "catid": 1,
        "account_type": "1",
        "customer_salutation": "Mr.",
        "first_name": "Mr.",
        "last_name": "Jalil",
        "name": "Sparkle Distribution",
        "customer_name_display": "SPARKLE DISTRIBUTION",
        "code": "CUSD-1003",
        "address": null,
        "address2": null,
        "country_telephone": "AE|231",
        "contcat_person": "Mr.",
        "designation": "Purchase",
        "contcat_number": "+971 4 354 4101",
        "mobile": "+971 4 354 4101",
        "email": "jalil@sparkle.com",
        "sales_person": 132,
        "vat_type": "",
        "purchase_type": null,
        "customer_type": 5,
        "sale_type": 5,
        "supplier_type": null,
        "vat_country": "231",
        "vat_state": "3391",
        "vat_percentage": "5",
        "vat_number": "01234564",
        "credit_limit": "100000.000",
        "credit_days": 60,
        "payment_terms": 8,
        "payment_terms_txt": "",
        "transaction_type": "Credit",
        "customer_documents": null,
        "status": 1,
        "created_by": 1,
        "updated_by": 1,
        "created_at": "2026-02-02 14:16:41",
        "updated_at": "2026-02-02 18:16:41",
        "type": 1,
        "company_id": 1,
        "vat_is_fixed": 0,
        "city": "Bur Dubai",
        "zip_code": "123456",
        "company_access": "1",
        "is_file": 1,
        "vendor_name": null,
        "beneficiary_name": null,
        "iban": null,
        "swift_code": null,
        "city_country": null,
        "stl": 0,
        "stl_bank": null,
        "stl_limit": null,
        "stl_per_trn_limit": null,
        "stl_opb": null,
        "internal": 0,
        "area": "Bank Street Building",
        "building_name": "Attrium Center",
        "flat_office_no": "105",
        "website": "http:\/\/www.sparkledistribution.com\/",
        "maps_location": "https:\/\/maps.google.com\/?cid=11119618803745990451",
        "place_id": "ChIJSfjdSdtDXz4RM6cIQ2PSUJo",
        "taken_from_stock": null,
        "stock_order": null,
        "customer_id": null,
        "supplier_id": null,
        "company_ship_to_id": null,
        "grn_select": null
    },
    {
        "id": 12,
        "created_by_company": null,
        "group": 1,
        "catid": 1,
        "account_type": "2",
        "customer_salutation": null,
        "first_name": "Mr.",
        "last_name": "Saju",
        "name": "GluCare.Health - Jumeirah",
        "customer_name_display": "GLUCARE.HEALTH - JUMEIRAH",
        "code": "CUSD-1004",
        "address": null,
        "address2": null,
        "country_telephone": "AE|231",
        "contcat_person": null,
        "designation": "Purchase",
        "contcat_number": "+971 800 4582273",
        "mobile": "+971 800 4582273",
        "email": "Saju@glucare.com",
        "sales_person": 132,
        "vat_type": "",
        "purchase_type": null,
        "customer_type": 5,
        "sale_type": 5,
        "supplier_type": null,
        "vat_country": "231",
        "vat_state": "3391",
        "vat_percentage": "5",
        "vat_number": "1234564",
        "credit_limit": "1.000",
        "credit_days": 1,
        "payment_terms": 3,
        "payment_terms_txt": null,
        "transaction_type": null,
        "customer_documents": null,
        "status": 3,
        "created_by": 1,
        "updated_by": 1,
        "created_at": "2026-01-30 18:08:54",
        "updated_at": "2026-01-30 22:08:54",
        "type": 1,
        "company_id": 1,
        "vat_is_fixed": 0,
        "city": null,
        "zip_code": null,
        "company_access": "1,1",
        "is_file": 1,
        "vendor_name": null,
        "beneficiary_name": null,
        "iban": null,
        "swift_code": null,
        "city_country": null,
        "stl": 0,
        "stl_bank": null,
        "stl_limit": null,
        "stl_per_trn_limit": null,
        "stl_opb": null,
        "internal": 0,
        "area": "Jumeirah 1",
        "building_name": "vill a",
        "flat_office_no": "104",
        "website": "http:\/\/www.glucare.health\/?utm_source=google&utm_medium=organic&utm_campaign=gmb",
        "maps_location": "https:\/\/maps.google.com\/?cid=7427773281464253335",
        "place_id": "ChIJ68EEiMJDXz4Rl3vQCXLAFGc",
        "taken_from_stock": null,
        "stock_order": null,
        "customer_id": null,
        "supplier_id": null,
        "company_ship_to_id": null,
        "grn_select": null
    },
    {
        "id": 13,
        "created_by_company": null,
        "group": 1,
        "catid": 1,
        "account_type": "1",
        "customer_salutation": "Mr.",
        "first_name": "Mr.",
        "last_name": "Paulo",
        "name": "Holiday Factory",
        "customer_name_display": "HOLIDAY FACTORY",
        "code": "CUSD-1005",
        "address": null,
        "address2": null,
        "country_telephone": "AE|231",
        "contcat_person": "Mr.",
        "designation": "Purchase",
        "contcat_number": "+971 4 701 4000",
        "mobile": "+971 4 701 4000",
        "email": "paulo@holiday.com",
        "sales_person": 132,
        "vat_type": "",
        "purchase_type": null,
        "customer_type": 5,
        "sale_type": 5,
        "supplier_type": null,
        "vat_country": "231",
        "vat_state": "3391",
        "vat_percentage": "5",
        "vat_number": "134642123",
        "credit_limit": "0.000",
        "credit_days": 0,
        "payment_terms": 1,
        "payment_terms_txt": "",
        "transaction_type": "Cash",
        "customer_documents": null,
        "status": 1,
        "created_by": 1,
        "updated_by": 133,
        "created_at": "2026-01-30 20:31:51",
        "updated_at": "2026-01-31 00:31:51",
        "type": 1,
        "company_id": 1,
        "vat_is_fixed": 0,
        "city": "Business Bay",
        "zip_code": "123",
        "company_access": "1",
        "is_file": 1,
        "vendor_name": null,
        "beneficiary_name": null,
        "iban": null,
        "swift_code": null,
        "city_country": null,
        "stl": 0,
        "stl_bank": null,
        "stl_limit": null,
        "stl_per_trn_limit": null,
        "stl_opb": null,
        "internal": 0,
        "area": "Business Bay",
        "building_name": "One by Omniyat",
        "flat_office_no": "103",
        "website": "http:\/\/www.holiday-factory.com\/",
        "maps_location": "https:\/\/maps.google.com\/?cid=16724717283730111832",
        "place_id": "ChIJEzS3XkRpXz4RWL2RGcIhGug",
        "taken_from_stock": null,
        "stock_order": null,
        "customer_id": null,
        "supplier_id": null,
        "company_ship_to_id": null,
        "grn_select": null
    },
    {
        "id": 14,
        "created_by_company": null,
        "group": 2,
        "catid": 2,
        "account_type": "1",
        "customer_salutation": "Mr",
        "first_name": "Zubair",
        "last_name": "Khan",
        "name": "WESTCON MIDDLE EAST EQUIPMENTS TRADING LLC",
        "customer_name_display": "WESTCON MIDDLE EAST EQUIPMENTS TRADING LLC",
        "code": "SUPD-1002",
        "address": null,
        "address2": null,
        "country_telephone": "AE|231",
        "contcat_person": "Zubair",
        "designation": "Account Manager",
        "contcat_number": "+971 4 8839888",
        "mobile": "+97154487867",
        "email": "zubai@westcon.com",
        "sales_person": 1,
        "vat_type": null,
        "purchase_type": 6,
        "customer_type": null,
        "sale_type": null,
        "supplier_type": 5,
        "vat_country": "231",
        "vat_state": "3391",
        "vat_percentage": "5",
        "vat_number": "100055202400003",
        "credit_limit": "1000000.000",
        "credit_days": 60,
        "payment_terms": 12,
        "payment_terms_txt": "",
        "transaction_type": "Credit",
        "customer_documents": null,
        "status": 1,
        "created_by": 1,
        "updated_by": null,
        "created_at": "2026-01-31 20:29:41",
        "updated_at": "2026-01-31 22:29:41",
        "type": 1,
        "company_id": 1,
        "vat_is_fixed": 0,
        "city": "Jabel Ali",
        "zip_code": null,
        "company_access": "1",
        "is_file": 1,
        "vendor_name": "",
        "beneficiary_name": "",
        "iban": "",
        "swift_code": "",
        "city_country": "",
        "stl": 0,
        "stl_bank": null,
        "stl_limit": null,
        "stl_per_trn_limit": null,
        "stl_opb": null,
        "internal": 0,
        "area": "ABC",
        "building_name": "DEF",
        "flat_office_no": "122",
        "website": "",
        "maps_location": "",
        "place_id": null,
        "taken_from_stock": null,
        "stock_order": null,
        "customer_id": null,
        "supplier_id": null,
        "company_ship_to_id": null,
        "grn_select": null
    },
    {
        "id": 15,
        "created_by_company": null,
        "group": 2,
        "catid": 2,
        "account_type": "2",
        "customer_salutation": "Mr",
        "first_name": "Arshad",
        "last_name": "Khan",
        "name": "GREEN LION TRADING FZE",
        "customer_name_display": "GREEN LION TRADING FZE",
        "code": "SUPD-1003",
        "address": null,
        "address2": null,
        "country_telephone": "AE|231",
        "contcat_person": "Arshad",
        "designation": "Managing Director",
        "contcat_number": "+971 48866331",
        "mobile": "+971 528863241",
        "email": "arshad@greenlion",
        "sales_person": 1,
        "vat_type": null,
        "purchase_type": 6,
        "customer_type": null,
        "sale_type": null,
        "supplier_type": 5,
        "vat_country": "231",
        "vat_state": "3391",
        "vat_percentage": "5",
        "vat_number": "",
        "credit_limit": "0.000",
        "credit_days": 0,
        "payment_terms": 3,
        "payment_terms_txt": "",
        "transaction_type": "Cash",
        "customer_documents": null,
        "status": 1,
        "created_by": 1,
        "updated_by": null,
        "created_at": "2026-02-02 18:06:50",
        "updated_at": "2026-02-02 20:06:50",
        "type": 1,
        "company_id": 1,
        "vat_is_fixed": 0,
        "city": "Jabel Ali",
        "zip_code": null,
        "company_access": "1",
        "is_file": 1,
        "vendor_name": "",
        "beneficiary_name": "",
        "iban": "",
        "swift_code": "",
        "city_country": "",
        "stl": 0,
        "stl_bank": null,
        "stl_limit": null,
        "stl_per_trn_limit": null,
        "stl_opb": null,
        "internal": 0,
        "area": "Freezone",
        "building_name": "shed 2563",
        "flat_office_no": "053",
        "website": "",
        "maps_location": "",
        "place_id": null,
        "taken_from_stock": null,
        "stock_order": null,
        "customer_id": null,
        "supplier_id": null,
        "company_ship_to_id": null,
        "grn_select": null
    },
    {
        "id": 16,
        "created_by_company": null,
        "group": 1,
        "catid": 1,
        "account_type": "1",
        "customer_salutation": "Mr.",
        "first_name": "Kanan",
        "last_name": "Desai",
        "name": "Future generation computer llc dubai",
        "customer_name_display": "FUTURE GENERATION COMPUTER LLC DUBAI",
        "code": "CUSD-1006",
        "address": null,
        "address2": null,
        "country_telephone": "AE|231",
        "contcat_person": "Kanan",
        "designation": "Procurement Manager",
        "contcat_number": "+971 4 352 2290",
        "mobile": "+971 526681213",
        "email": "kanan@future",
        "sales_person": 1,
        "vat_type": null,
        "purchase_type": null,
        "customer_type": 5,
        "sale_type": 5,
        "supplier_type": null,
        "vat_country": "231",
        "vat_state": "3391",
        "vat_percentage": "5",
        "vat_number": "13456464",
        "credit_limit": "100000.000",
        "credit_days": 60,
        "payment_terms": 9,
        "payment_terms_txt": "",
        "transaction_type": "Credit",
        "customer_documents": null,
        "status": 1,
        "created_by": 1,
        "updated_by": null,
        "created_at": "2026-02-03 22:30:56",
        "updated_at": "2026-02-04 00:30:56",
        "type": 1,
        "company_id": 1,
        "vat_is_fixed": 0,
        "city": "Bur Dubai",
        "zip_code": "",
        "company_access": "1",
        "is_file": 1,
        "vendor_name": null,
        "beneficiary_name": null,
        "iban": null,
        "swift_code": null,
        "city_country": null,
        "stl": 0,
        "stl_bank": null,
        "stl_limit": null,
        "stl_per_trn_limit": null,
        "stl_opb": null,
        "internal": 0,
        "area": "Al Raffa",
        "building_name": "Al Raffa building",
        "flat_office_no": "12345",
        "website": "",
        "maps_location": "https:\/\/maps.google.com\/?cid=6761112696741091432",
        "place_id": "ChIJk8hQobxDXz4RaNii_yxM1F0",
        "taken_from_stock": null,
        "stock_order": null,
        "customer_id": null,
        "supplier_id": null,
        "company_ship_to_id": null,
        "grn_select": null
    },
    {
        "id": 17,
        "created_by_company": null,
        "group": 1,
        "catid": 1,
        "account_type": "1",
        "customer_salutation": "Mr.",
        "first_name": "HAMID",
        "last_name": "ANSRI",
        "name": "Endless Data Computer",
        "customer_name_display": "ENDLESS DATA COMPUTER",
        "code": "CUSD-1007",
        "address": null,
        "address2": null,
        "country_telephone": "AE|231",
        "contcat_person": "HAMID",
        "designation": "Purchase",
        "contcat_number": "+971 4 355 7526",
        "mobile": "+971 4 355 7526",
        "email": "hamid@sys.com",
        "sales_person": 132,
        "vat_type": "",
        "purchase_type": null,
        "customer_type": 5,
        "sale_type": 5,
        "supplier_type": null,
        "vat_country": "231",
        "vat_state": "3391",
        "vat_percentage": "5",
        "vat_number": "123456",
        "credit_limit": "1.000",
        "credit_days": 1,
        "payment_terms": 6,
        "payment_terms_txt": "",
        "transaction_type": "Credit",
        "customer_documents": null,
        "status": 1,
        "created_by": 1,
        "updated_by": 1,
        "created_at": "2026-02-07 18:19:40",
        "updated_at": "2026-02-07 22:19:40",
        "type": 1,
        "company_id": 1,
        "vat_is_fixed": 0,
        "city": "Bur Dubai",
        "zip_code": "132456",
        "company_access": "1,3",
        "is_file": 1,
        "vendor_name": null,
        "beneficiary_name": null,
        "iban": null,
        "swift_code": null,
        "city_country": null,
        "stl": 0,
        "stl_bank": null,
        "stl_limit": null,
        "stl_per_trn_limit": null,
        "stl_opb": null,
        "internal": 0,
        "area": "Al Souq Al Kabeer",
        "building_name": "Al Fahidi",
        "flat_office_no": "105",
        "website": "http:\/\/www.edatame.com\/",
        "maps_location": "https:\/\/maps.google.com\/?cid=14743156642331457327",
        "place_id": "ChIJkcl6dRVDXz4RL3cbhto2msw",
        "taken_from_stock": null,
        "stock_order": null,
        "customer_id": null,
        "supplier_id": null,
        "company_ship_to_id": null,
        "grn_select": null
    },
    {
        "id": 18,
        "created_by_company": null,
        "group": 2,
        "catid": 2,
        "account_type": "1",
        "customer_salutation": "Mr.",
        "first_name": "Ahmed",
        "last_name": "Khan",
        "name": "Mindware Technology Trading LLC",
        "customer_name_display": "MINDWARE TECHNOLOGY TRADING LLC",
        "code": "SUPD-1004",
        "address": null,
        "address2": null,
        "country_telephone": "AE|231",
        "contcat_person": "Ahmed",
        "designation": "Account Manager",
        "contcat_number": "+971 4 450 0600",
        "mobile": "+971 4 450 0600",
        "email": "ahmed@mindware.ae",
        "sales_person": 1,
        "vat_type": null,
        "purchase_type": 6,
        "customer_type": null,
        "sale_type": null,
        "supplier_type": 5,
        "vat_country": "231",
        "vat_state": "3391",
        "vat_percentage": "5",
        "vat_number": "123456",
        "credit_limit": "100000.000",
        "credit_days": 60,
        "payment_terms": 8,
        "payment_terms_txt": "",
        "transaction_type": "Credit",
        "customer_documents": null,
        "status": 1,
        "created_by": 1,
        "updated_by": 1,
        "created_at": "2026-02-07 18:36:30",
        "updated_at": "2026-02-07 22:36:30",
        "type": 1,
        "company_id": 1,
        "vat_is_fixed": 0,
        "city": "Jabel Ali",
        "zip_code": "123456",
        "company_access": "1,3",
        "is_file": 1,
        "vendor_name": "",
        "beneficiary_name": "",
        "iban": "",
        "swift_code": "",
        "city_country": "",
        "stl": 0,
        "stl_bank": null,
        "stl_limit": null,
        "stl_per_trn_limit": null,
        "stl_opb": null,
        "internal": 0,
        "area": "Free zone",
        "building_name": "Al Thanyah First",
        "flat_office_no": "012",
        "website": "http:\/\/www.mindware.net\/",
        "maps_location": "https:\/\/maps.google.com\/?cid=8886512197364600737",
        "place_id": null,
        "taken_from_stock": null,
        "stock_order": null,
        "customer_id": null,
        "supplier_id": null,
        "company_ship_to_id": null,
        "grn_select": null
    },
    {
        "id": 19,
        "created_by_company": null,
        "group": 1,
        "catid": 1,
        "account_type": "2",
        "customer_salutation": "Mr.",
        "first_name": "Muhammad Sohail",
        "last_name": "Akhtar",
        "name": "Ajman Specialty General Hospital",
        "customer_name_display": "AJMAN SPECIALTY GENERAL HOSPITAL",
        "code": "CUSIT-1001",
        "address": null,
        "address2": null,
        "country_telephone": "AE|231",
        "contcat_person": "Muhammad Sohail",
        "designation": "Procurement Manager",
        "contcat_number": "+9716 705 2200",
        "mobile": "+9716 705 2200",
        "email": "sohail@aj.sh.com",
        "sales_person": 1,
        "vat_type": null,
        "purchase_type": null,
        "customer_type": 5,
        "sale_type": 5,
        "supplier_type": null,
        "vat_country": "231",
        "vat_state": "3395",
        "vat_percentage": "5",
        "vat_number": "100313479600003",
        "credit_limit": "0.000",
        "credit_days": 0,
        "payment_terms": 1,
        "payment_terms_txt": "",
        "transaction_type": "Cash",
        "customer_documents": null,
        "status": 1,
        "created_by": 1,
        "updated_by": 1,
        "created_at": "2026-03-18 13:53:06",
        "updated_at": "2026-03-18 17:53:06",
        "type": 1,
        "company_id": 3,
        "vat_is_fixed": 0,
        "city": "Shaik Al Maktoom Street",
        "zip_code": "Near Irani Market",
        "company_access": "1,3",
        "is_file": 1,
        "vendor_name": null,
        "beneficiary_name": null,
        "iban": null,
        "swift_code": null,
        "city_country": null,
        "stl": 0,
        "stl_bank": null,
        "stl_limit": null,
        "stl_per_trn_limit": null,
        "stl_opb": null,
        "internal": 0,
        "area": "Industrial Area 1",
        "building_name": "Near Irani Market",
        "flat_office_no": "12",
        "website": "http:\/\/www.aj-sh.com\/.",
        "maps_location": "https:\/\/maps.google.com\/?cid=6432661543087220400",
        "place_id": "ChIJUdy-E3JYXz4RsKYHfJdnRVk",
        "taken_from_stock": null,
        "stock_order": null,
        "customer_id": null,
        "supplier_id": null,
        "company_ship_to_id": null,
        "grn_select": null
    },
    {
        "id": 20,
        "created_by_company": null,
        "group": 1,
        "catid": 1,
        "account_type": "1",
        "customer_salutation": "Mr.",
        "first_name": "Saneesh",
        "last_name": "",
        "name": "Brass Monkey - Bluewaters",
        "customer_name_display": "BRASS MONKEY - BLUEWATERS",
        "code": "CUSD-1008",
        "address": null,
        "address2": null,
        "country_telephone": "AE|231",
        "contcat_person": "Saneesh",
        "designation": "Purchase",
        "contcat_number": "+971 4 582 7277",
        "mobile": "+971 4 582 7277",
        "email": "hamid@sysllc.com",
        "sales_person": 132,
        "vat_type": "",
        "purchase_type": null,
        "customer_type": 5,
        "sale_type": 5,
        "supplier_type": null,
        "vat_country": "231",
        "vat_state": "3391",
        "vat_percentage": "5",
        "vat_number": "00214564654",
        "credit_limit": "1.000",
        "credit_days": 1,
        "payment_terms": 3,
        "payment_terms_txt": "",
        "transaction_type": "Credit",
        "customer_documents": null,
        "status": 1,
        "created_by": 1,
        "updated_by": 1,
        "created_at": "2026-03-10 13:29:48",
        "updated_at": "2026-03-10 17:29:48",
        "type": 1,
        "company_id": 1,
        "vat_is_fixed": 0,
        "city": "Marsa Dubai",
        "zip_code": "",
        "company_access": "1",
        "is_file": 1,
        "vendor_name": null,
        "beneficiary_name": null,
        "iban": null,
        "swift_code": null,
        "city_country": null,
        "stl": 0,
        "stl_bank": null,
        "stl_limit": null,
        "stl_per_trn_limit": null,
        "stl_opb": null,
        "internal": 0,
        "area": "Bluewaters Island",
        "building_name": "Bluewaters Island",
        "flat_office_no": null,
        "website": "https:\/\/brassmonkeysocial.com\/",
        "maps_location": "https:\/\/maps.google.com\/?cid=14940203298731491453",
        "place_id": "ChIJHYONX-cVXz4RfYACXb5DVs8",
        "taken_from_stock": null,
        "stock_order": null,
        "customer_id": null,
        "supplier_id": null,
        "company_ship_to_id": null,
        "grn_select": "yes"
    },
    {
        "id": 21,
        "created_by_company": null,
        "group": 1,
        "catid": 1,
        "account_type": "1",
        "customer_salutation": "Mr.",
        "first_name": "Mr.",
        "last_name": "Abu Thahir",
        "name": "REGAL COMPUTER TRADING LLC",
        "customer_name_display": "REGAL COMPUTER TRADING LLC",
        "code": "CUSD-1009",
        "address": null,
        "address2": null,
        "country_telephone": "AE|231",
        "contcat_person": null,
        "designation": "Purchase",
        "contcat_number": "+971 56 620 4058",
        "mobile": "+971 56 620 4058",
        "email": "info@regalcomputerllc.com",
        "sales_person": 132,
        "vat_type": "",
        "purchase_type": null,
        "customer_type": 5,
        "sale_type": 5,
        "supplier_type": null,
        "vat_country": "231",
        "vat_state": "3391",
        "vat_percentage": "5",
        "vat_number": "103365131",
        "credit_limit": "1.000",
        "credit_days": 1,
        "payment_terms": 3,
        "payment_terms_txt": null,
        "transaction_type": null,
        "customer_documents": null,
        "status": 3,
        "created_by": 1,
        "updated_by": 1,
        "created_at": "2026-02-19 13:20:49",
        "updated_at": "2026-02-19 17:20:49",
        "type": 1,
        "company_id": 1,
        "vat_is_fixed": 0,
        "city": null,
        "zip_code": null,
        "company_access": "1,1",
        "is_file": 1,
        "vendor_name": null,
        "beneficiary_name": null,
        "iban": null,
        "swift_code": null,
        "city_country": null,
        "stl": 0,
        "stl_bank": null,
        "stl_limit": null,
        "stl_per_trn_limit": null,
        "stl_opb": null,
        "internal": 0,
        "area": "Al Souq Al Kabeer",
        "building_name": "Al Fahidi",
        "flat_office_no": "102",
        "website": "https:\/\/www.regalcomputerllc.com\/",
        "maps_location": "https:\/\/maps.google.com\/?cid=16975534968587439736",
        "place_id": "ChIJcTit-VlDXz4ReE7gGh03les",
        "taken_from_stock": null,
        "stock_order": null,
        "customer_id": null,
        "supplier_id": null,
        "company_ship_to_id": null,
        "grn_select": null
    },
    {
        "id": 22,
        "created_by_company": null,
        "group": 2,
        "catid": 2,
        "account_type": "1",
        "customer_salutation": "Mr",
        "first_name": "SHANAWAZ",
        "last_name": "SIDDIQUI",
        "name": "Allied Telesis, Inc.",
        "customer_name_display": "ALLIED TELESIS, INC.",
        "code": "SUPD-1005",
        "address": null,
        "address2": null,
        "country_telephone": "US|233",
        "contcat_person": "SHANAWAZ",
        "designation": "Business Development Manager",
        "contcat_number": "+1 408-519-8700",
        "mobile": "+1 408-519-8700",
        "email": "shan@alliedtelesis.com",
        "sales_person": 1,
        "vat_type": null,
        "purchase_type": 6,
        "customer_type": null,
        "sale_type": null,
        "supplier_type": 5,
        "vat_country": "233",
        "vat_state": "1416",
        "vat_percentage": "0",
        "vat_number": "",
        "credit_limit": null,
        "credit_days": null,
        "payment_terms": 3,
        "payment_terms_txt": "",
        "transaction_type": "Cash",
        "customer_documents": null,
        "status": 1,
        "created_by": 1,
        "updated_by": null,
        "created_at": "2026-02-19 17:26:07",
        "updated_at": "2026-02-19 19:26:07",
        "type": 1,
        "company_id": 1,
        "vat_is_fixed": 0,
        "city": "San Jose",
        "zip_code": null,
        "company_access": "1",
        "is_file": 1,
        "vendor_name": "",
        "beneficiary_name": "",
        "iban": "",
        "swift_code": "",
        "city_country": "",
        "stl": 0,
        "stl_bank": null,
        "stl_limit": null,
        "stl_per_trn_limit": null,
        "stl_opb": null,
        "internal": 0,
        "area": "San Jose",
        "building_name": "hlsj",
        "flat_office_no": "102",
        "website": "http:\/\/www.alliedtelesis.com\/",
        "maps_location": "https:\/\/maps.google.com\/?cid=7253197358114880182",
        "place_id": null,
        "taken_from_stock": null,
        "stock_order": null,
        "customer_id": null,
        "supplier_id": null,
        "company_ship_to_id": null,
        "grn_select": null
    },
    {
        "id": 23,
        "created_by_company": null,
        "group": 1,
        "catid": 1,
        "account_type": "2",
        "customer_salutation": "Mr.",
        "first_name": "Vikas",
        "last_name": "Kumar",
        "name": "Afcons Construction Mideast Llc",
        "customer_name_display": "AFCONS CONSTRUCTION MIDEAST LLC",
        "code": "CUSD-1010",
        "address": null,
        "address2": null,
        "country_telephone": "AE|231",
        "contcat_person": "Vikas",
        "designation": "Purchase",
        "contcat_number": "+971 566831424",
        "mobile": "+971 566831424",
        "email": "kumar.vikas@afcons.com",
        "sales_person": 140,
        "vat_type": "",
        "purchase_type": null,
        "customer_type": 5,
        "sale_type": 5,
        "supplier_type": null,
        "vat_country": "231",
        "vat_state": "3391",
        "vat_percentage": "5",
        "vat_number": "1234567897",
        "credit_limit": "1.000",
        "credit_days": 1,
        "payment_terms": 6,
        "payment_terms_txt": "",
        "transaction_type": "Credit",
        "customer_documents": null,
        "status": 1,
        "created_by": 1,
        "updated_by": 1,
        "created_at": "2026-03-02 15:35:59",
        "updated_at": "2026-03-02 19:35:59",
        "type": 1,
        "company_id": 1,
        "vat_is_fixed": 0,
        "city": "Baghdad Street",
        "zip_code": "",
        "company_access": "1",
        "is_file": 1,
        "vendor_name": null,
        "beneficiary_name": null,
        "iban": null,
        "swift_code": null,
        "city_country": null,
        "stl": 0,
        "stl_bank": null,
        "stl_limit": null,
        "stl_per_trn_limit": null,
        "stl_opb": null,
        "internal": 0,
        "area": "Al Nahda 2",
        "building_name": "Platinum Business Centre",
        "flat_office_no": null,
        "website": "",
        "maps_location": "https:\/\/maps.google.com\/?cid=8507413834570335655",
        "place_id": "ChIJqwtVkxYLXz4RpwXP7s5nEHY",
        "taken_from_stock": null,
        "stock_order": null,
        "customer_id": null,
        "supplier_id": null,
        "company_ship_to_id": null,
        "grn_select": null
    },
    {
        "id": 24,
        "created_by_company": null,
        "group": 2,
        "catid": 2,
        "account_type": "1",
        "customer_salutation": "Miss",
        "first_name": "Anna",
        "last_name": "Strazhevich",
        "name": "Keyston Distribution LLC",
        "customer_name_display": "KEYSTON DISTRIBUTION LLC",
        "code": "SUPD-1006",
        "address": null,
        "address2": null,
        "country_telephone": "AE|231",
        "contcat_person": "Anna",
        "designation": "Account Manager",
        "contcat_number": "+971 4 665 4700",
        "mobile": "+971 4 665 4700",
        "email": "anna@Keyston Distribution LLC",
        "sales_person": 1,
        "vat_type": null,
        "purchase_type": 6,
        "customer_type": null,
        "sale_type": null,
        "supplier_type": 5,
        "vat_country": "231",
        "vat_state": "3391",
        "vat_percentage": "5",
        "vat_number": "100489055200003",
        "credit_limit": "1500000.000",
        "credit_days": 90,
        "payment_terms": 34,
        "payment_terms_txt": "",
        "transaction_type": "Credit",
        "customer_documents": null,
        "status": 1,
        "created_by": 1,
        "updated_by": null,
        "created_at": "2026-03-02 19:43:55",
        "updated_at": "2026-03-02 21:43:55",
        "type": 1,
        "company_id": 1,
        "vat_is_fixed": 0,
        "city": "Business Bay",
        "zip_code": null,
        "company_access": "1",
        "is_file": 1,
        "vendor_name": "",
        "beneficiary_name": "",
        "iban": "",
        "swift_code": "",
        "city_country": "",
        "stl": 0,
        "stl_bank": null,
        "stl_limit": null,
        "stl_per_trn_limit": null,
        "stl_opb": null,
        "internal": 0,
        "area": "Marasi Street",
        "building_name": "Binary Tower",
        "flat_office_no": "P 5",
        "website": "http:\/\/www.keyston.com\/",
        "maps_location": "https:\/\/maps.google.com\/?cid=8697884913876204304",
        "place_id": null,
        "taken_from_stock": null,
        "stock_order": null,
        "customer_id": null,
        "supplier_id": null,
        "company_ship_to_id": null,
        "grn_select": null
    }
]